MANIFEST.in
cython_additions.hpp
neighbour.cpp
neighbour.h
quadtree.cpp
quadtree.h
quadtree.hpp
setup.py
smartquadtree.cpp
smartquadtree.pyx
tutorial.rst
cglacet_smartquadtree.egg-info/PKG-INFO
cglacet_smartquadtree.egg-info/SOURCES.txt
cglacet_smartquadtree.egg-info/dependency_links.txt
cglacet_smartquadtree.egg-info/top_level.txt