Metadata-Version: 1.0
Name: cglacet-smartquadtree
Version: 1.1.5
Summary: Implementation of quadtrees for moving objects
Home-page: https://github.com/cglacet/quadtree
Author: Xavier Olive
Author-email: xavier@xoolive.org
License: MIT
Platform: UNKNOWN
